shipyard_scraper_api/__init__.py
shipyard_scraper_api/scraper-api.py
shipyard_scraper_api/cli/__init__.py
shipyard_scraper_api/cli/authtest.py
shipyard_scraper_api/cli/take_screenshot.py
shipyard_scraper_api/utils/take-screenshot.py
shipyard_scraper_api/utils/utils.py
shipyard_scraper_api-0.1.1a1.dist-info/METADATA
shipyard_scraper_api-0.1.1a1.dist-info/WHEEL
shipyard_scraper_api-0.1.1a1.dist-info/top_level.txt
shipyard_scraper_api-0.1.1a1.dist-info/RECORD
