Metadata-Version: 2.4
Name: shipyard-scraper-api
Version: 0.1.1a1
Summary: A local client for connecting and working with Databricks
Requires-Python: >=3.9
Requires-Dist: requests>=2.32.3
Requires-Dist: shipyard-templates>=0.9.0
